pychubby/__init__.py
pychubby/actions.py
pychubby/base.py
pychubby/cli.py
pychubby/data.py
pychubby/detect.py
pychubby/reference.py
pychubby/utils.py
pychubby/visualization.py
pychubby-0.2.dist-info/LICENSE
pychubby-0.2.dist-info/METADATA
pychubby-0.2.dist-info/WHEEL
pychubby-0.2.dist-info/entry_points.txt
pychubby-0.2.dist-info/top_level.txt
pychubby-0.2.dist-info/RECORD
